<?xml version="1.0" encoding="utf-8"?>
<!DOCTYPE hibernate-mapping PUBLIC "-//Hibernate/Hibernate Mapping DTD 3.0//EN"
"http://hibernate.sourceforge.net/hibernate-mapping-3.0.dtd">
<!-- 
    Mapping file autogenerated by MyEclipse Persistence Tools
-->
<hibernate-mapping>
    <class name="com.aaa.entity.Jobtitle" table="jobtitle" catalog="ops">
        <id name="jobTitleId" type="java.lang.Integer">
            <column name="JobTitleId" />
            <generator class="native"></generator>
        </id>
        <property name="jobTitleName" type="java.lang.String">
            <column name="JobTitleName" length="50" />
        </property>
        <set name="stuffs" inverse="true">
            <key>
                <column name="JobTitleId" />
            </key>
            <one-to-many class="com.aaa.entity.Stuff" />
        </set>
    </class>
</hibernate-mapping>
