<?xml version="1.0" encoding="UTF-8"?>
<!DOCTYPE hibernate-reverse-engineering PUBLIC "-//Hibernate/Hibernate Reverse Engineering DTD 3.0//EN" "http://hibernate.sourceforge.net/hibernate-reverse-engineering-3.0.dtd" >

<hibernate-reverse-engineering>
	<table name="accounts" catalog="ops">
		<primary-key>
			<generator class="native"></generator>
		</primary-key>
	</table>
	<table name="advice" catalog="ops">
		<primary-key>
			<generator class="native"></generator>
		</primary-key>
	</table>
	<table name="adviceinfo" catalog="ops">
		<primary-key>
			<generator class="native"></generator>
		</primary-key>
	</table>
	<table name="bed" catalog="ops">
		<primary-key>
			<generator class="native"></generator>
		</primary-key>
	</table>
	<table name="bqtype" catalog="ops">
		<primary-key>
			<generator class="native"></generator>
		</primary-key>
	</table>
	<table name="buliding" catalog="ops">
		<primary-key>
			<generator class="native"></generator>
		</primary-key>
	</table>
	<table name="charge" catalog="ops">
		<primary-key>
			<generator class="native"></generator>
		</primary-key>
	</table>
	<table name="checktype" catalog="ops">
		<primary-key>
			<generator class="native"></generator>
		</primary-key>
	</table>
	<table name="chinesedetails" catalog="ops">
		<primary-key>
			<generator class="native"></generator>
		</primary-key>
	</table>
	<table name="chineseprescribe" catalog="ops">
		<primary-key>
			<generator class="native"></generator>
		</primary-key>
	</table>
	<table name="clinicregister" catalog="ops">
		<primary-key>
			<generator class="native"></generator>
		</primary-key>
	</table>
	<table name="contactperson" catalog="ops">
		<primary-key>
			<generator class="native"></generator>
		</primary-key>
	</table>
	<table name="cure" catalog="ops">
		<primary-key>
			<generator class="native"></generator>
		</primary-key>
	</table>
	<table name="department" catalog="ops">
		<primary-key>
			<generator class="native"></generator>
		</primary-key>
	</table>
	<table name="departmenttype" catalog="ops">
		<primary-key>
			<generator class="native"></generator>
		</primary-key>
	</table>
	<table name="doctor" catalog="ops">
		<primary-key>
			<generator class="native"></generator>
		</primary-key>
	</table>
	<table name="doctorwork" catalog="ops">
		<primary-key>
			<generator class="native"></generator>
		</primary-key>
	</table>
	<table name="docworklog" catalog="ops">
		<primary-key>
			<generator class="native"></generator>
		</primary-key>
	</table>
	<table name="examineorder" catalog="ops">
		<primary-key>
			<generator class="native"></generator>
		</primary-key>
	</table>
	<table name="examineresult" catalog="ops">
		<primary-key>
			<generator class="native"></generator>
		</primary-key>
	</table>
	<table name="floor" catalog="ops">
		<primary-key>
			<generator class="native"></generator>
		</primary-key>
	</table>
	<table name="icclip" catalog="ops">
		<primary-key>
			<generator class="native"></generator>
		</primary-key>
	</table>
	<table name="illnesscase" catalog="ops">
		<primary-key>
			<generator class="native"></generator>
		</primary-key>
	</table>
	<table name="inpatientarea" catalog="ops">
		<primary-key>
			<generator class="native"></generator>
		</primary-key>
	</table>
	<table name="jobtitle" catalog="ops">
		<primary-key>
			<generator class="native"></generator>
		</primary-key>
	</table>
	<table name="medicalrecord" catalog="ops">
		<primary-key>
			<generator class="native"></generator>
		</primary-key>
	</table>
	<table name="nurse_watch" catalog="ops">
		<primary-key>
			<generator class="native"></generator>
		</primary-key>
	</table>
	<table name="nurworklog" catalog="ops">
		<primary-key>
			<generator class="native"></generator>
		</primary-key>
	</table>
	<table name="outhospital" catalog="ops">
		<primary-key>
			<generator class="native"></generator>
		</primary-key>
	</table>
	<table name="outhosstate" catalog="ops">
		<primary-key>
			<generator class="native"></generator>
		</primary-key>
	</table>
	<table name="particulars" catalog="ops">
		<primary-key>
			<generator class="native"></generator>
		</primary-key>
	</table>
	<table name="patient2" catalog="ops">
		<primary-key>
			<generator class="native"></generator>
		</primary-key>
	</table>
	<table name="patient" catalog="ops">
		<primary-key>
			<generator class="native"></generator>
		</primary-key>
	</table>
	<table name="position" catalog="ops">
		<primary-key>
			<generator class="native"></generator>
		</primary-key>
	</table>
	<table name="relationship_42" catalog="ops">
		<primary-key>
			<generator class="native"></generator>
		</primary-key>
	</table>
	<table name="room" catalog="ops">
		<primary-key>
			<generator class="native"></generator>
		</primary-key>
	</table>
	<table name="sort" catalog="ops">
		<primary-key>
			<generator class="native"></generator>
		</primary-key>
	</table>
	<table name="stuff" catalog="ops">
		<primary-key>
			<generator class="native"></generator>
		</primary-key>
	</table>
	<table name="stufftype" catalog="ops">
		<primary-key>
			<generator class="native"></generator>
		</primary-key>
	</table>
	<table name="subscribe" catalog="ops">
		<primary-key>
			<generator class="native"></generator>
		</primary-key>
	</table>
	<table name="triage" catalog="ops">
		<primary-key>
			<generator class="native"></generator>
		</primary-key>
	</table>
	<table name="watebill" catalog="ops">
		<primary-key>
			<generator class="native"></generator>
		</primary-key>
	</table>
	<table name="westerndetails" catalog="ops">
		<primary-key>
			<generator class="native"></generator>
		</primary-key>
	</table>
	<table name="westernprescribe" catalog="ops">
		<primary-key>
			<generator class="native"></generator>
		</primary-key>
	</table>
<table name="yzmoid" catalog="ops">
	<primary-key>
		<generator class="native"></generator>
	</primary-key>
</table>
</hibernate-reverse-engineering>